model_compare/__init__.py
model_compare/main.py
model_compare/prompts.py
model_compare-2025.12.22083425.dist-info/METADATA
model_compare-2025.12.22083425.dist-info/WHEEL
model_compare-2025.12.22083425.dist-info/top_level.txt
model_compare-2025.12.22083425.dist-info/RECORD
