Metadata-Version: 2.4
Name: model-compare
Version: 2025.12.22083425
Summary: model-compare evaluates AI models side‑by‑side based on user tasks, rating accuracy, creativity, and efficiency to guide model choice.
Author-email: model-compare <hi@eugene.plus>
License: MIT
Project-URL: Homepage, https://github.com/chigwell/model-compare
Requires-Python: >=3.9
Requires-Dist: langchain-llm7>=0.0.0
Requires-Dist: llmatch-messages>=0.0.0
Requires-Dist: langchain-core>=0.3.0
